pyorb.cpython-39-x86_64-linux-gnu.so
pyorbfeature-0.1.7.dist-info/LICENSE
pyorbfeature-0.1.7.dist-info/METADATA
pyorbfeature-0.1.7.dist-info/WHEEL
pyorbfeature-0.1.7.dist-info/top_level.txt
pyorbfeature-0.1.7.dist-info/RECORD
