Metadata-Version: 2.1
Name: pyorbfeature
Version: 0.1.7
Summary: PYORB bindings
Home-page: UNKNOWN
Author: xinli
Author-email: lisin97@pku.edu.cn
License: UNKNOWN
Platform: UNKNOWN
License-File: LICENSE
